{
  "neoforge:conditions": [
    {
      "type": "neoforge:mod_loaded",
      "modid": "firmalife"
    }
  ],
  "type": "tfc:cluster_vein",
  "config": {
    "rarity": 50,
    "density": 0.25,
    "min_y": 40,
    "max_y": 130,
    "random_name": 3541562012782510535,
    "blocks": [
      {
        "replace": [
          "minecraft:granite"
        ],
        "with": [
          {
            "block": "firma_compat:poor_granite_chromite_ore",
            "weight": 35.0
          },
          {
            "block": "firma_compat:normal_granite_chromite_ore",
            "weight": 40.0
          },
          {
            "block": "firma_compat:rich_granite_chromite_ore",
            "weight": 25.0
          }
        ]
      },
      {
        "replace": [
          "minecraft:diorite"
        ],
        "with": [
          {
            "block": "firma_compat:poor_diorite_chromite_ore",
            "weight": 35.0
          },
          {
            "block": "firma_compat:normal_diorite_chromite_ore",
            "weight": 40.0
          },
          {
            "block": "firma_compat:rich_diorite_chromite_ore",
            "weight": 25.0
          }
        ]
      },
      {
        "replace": [
          "minecraft:deepslate"
        ],
        "with": [
          {
            "block": "firma_compat:poor_deepslate_chromite_ore",
            "weight": 35.0
          },
          {
            "block": "firma_compat:normal_deepslate_chromite_ore",
            "weight": 40.0
          },
          {
            "block": "firma_compat:rich_deepslate_chromite_ore",
            "weight": 25.0
          }
        ]
      },
      {
        "replace": [
          "minecraft:andesite"
        ],
        "with": [
          {
            "block": "firma_compat:poor_andesite_chromite_ore",
            "weight": 35.0
          },
          {
            "block": "firma_compat:normal_andesite_chromite_ore",
            "weight": 40.0
          },
          {
            "block": "firma_compat:rich_andesite_chromite_ore",
            "weight": 25.0
          }
        ]
      },
      {
        "replace": [
          "minecraft:basalt"
        ],
        "with": [
          {
            "block": "firma_compat:poor_basalt_chromite_ore",
            "weight": 35.0
          },
          {
            "block": "firma_compat:normal_basalt_chromite_ore",
            "weight": 40.0
          },
          {
            "block": "firma_compat:rich_basalt_chromite_ore",
            "weight": 25.0
          }
        ]
      },
      {
        "replace": [
          "minecraft:calcite"
        ],
        "with": [
          {
            "block": "firma_compat:poor_calcite_chromite_ore",
            "weight": 35.0
          },
          {
            "block": "firma_compat:normal_calcite_chromite_ore",
            "weight": 40.0
          },
          {
            "block": "firma_compat:rich_calcite_chromite_ore",
            "weight": 25.0
          }
        ]
      },
      {
        "replace": [
          "minecraft:tuff"
        ],
        "with": [
          {
            "block": "firma_compat:poor_tuff_chromite_ore",
            "weight": 35.0
          },
          {
            "block": "firma_compat:normal_tuff_chromite_ore",
            "weight": 40.0
          },
          {
            "block": "firma_compat:rich_tuff_chromite_ore",
            "weight": 25.0
          }
        ]
      },
      {
        "replace": [
          "minecraft:dripstone_block"
        ],
        "with": [
          {
            "block": "firma_compat:poor_dripstone_chromite_ore",
            "weight": 35.0
          },
          {
            "block": "firma_compat:normal_dripstone_chromite_ore",
            "weight": 40.0
          },
          {
            "block": "firma_compat:rich_dripstone_chromite_ore",
            "weight": 25.0
          }
        ]
      },
      {
        "replace": [
          "minecraft:stone"
        ],
        "with": [
          {
            "block": "firma_compat:poor_stone_chromite_ore",
            "weight": 35.0
          },
          {
            "block": "firma_compat:normal_stone_chromite_ore",
            "weight": 40.0
          },
          {
            "block": "firma_compat:rich_stone_chromite_ore",
            "weight": 25.0
          }
        ]
      },
      {
        "replace": [
          "minecraft:blackstone"
        ],
        "with": [
          {
            "block": "firma_compat:poor_blackstone_chromite_ore",
            "weight": 35.0
          },
          {
            "block": "firma_compat:normal_blackstone_chromite_ore",
            "weight": 40.0
          },
          {
            "block": "firma_compat:rich_blackstone_chromite_ore",
            "weight": 25.0
          }
        ]
      },
      {
        "replace": [
          "minecraft:netherrack"
        ],
        "with": [
          {
            "block": "firma_compat:poor_netherrack_chromite_ore",
            "weight": 35.0
          },
          {
            "block": "firma_compat:normal_netherrack_chromite_ore",
            "weight": 40.0
          },
          {
            "block": "firma_compat:rich_netherrack_chromite_ore",
            "weight": 25.0
          }
        ]
      },
      {
        "replace": [
          "minecraft:end_stone"
        ],
        "with": [
          {
            "block": "firma_compat:poor_end_stone_chromite_ore",
            "weight": 35.0
          },
          {
            "block": "firma_compat:normal_end_stone_chromite_ore",
            "weight": 40.0
          },
          {
            "block": "firma_compat:rich_end_stone_chromite_ore",
            "weight": 25.0
          }
        ]
      }
    ],
    "size": 8
  }
}